kisters/water/time_series/core/__init__.py
kisters/water/time_series/core/exceptions.py
kisters/water/time_series/core/py.typed
kisters/water/time_series/core/schema.py
kisters/water/time_series/core/time_series.py
kisters/water/time_series/core/time_series_store.py
kisters/water/time_series/core/utils.py
kisters/water/time_series/core/time_series_client/__init__.py
kisters/water/time_series/core/time_series_client/old_ts_client.py
kisters/water/time_series/core/time_series_client/py.typed
kisters/water/time_series/core/time_series_client/synchronous_ts_client.py
kisters/water/time_series/core/time_series_client/time_series_client.py
kisters/water/time_series/core/time_series_client/ts_client_helper.py
kisters/water/time_series/kiwis/__init__.py
kisters/water/time_series/kiwis/async_auto_retry_client.py
kisters/water/time_series/kiwis/exceptions.py
kisters/water/time_series/kiwis/kiwis_store.py
kisters/water/time_series/kiwis/kiwis_time_series_client.py
kisters/water/time_series/kiwis/py.typed
kisters/water/time_series/memory/__init__.py
kisters/water/time_series/memory/memory_store.py
kisters/water/time_series/memory/memory_time_series_client.py
kisters/water/time_series/memory/py.typed
kisters/water/time_series/parquet/__init__.py
kisters/water/time_series/parquet/parquet_store.py
kisters/water/time_series/parquet/parquet_time_series_client.py
kisters/water/time_series/parquet/py.typed
kisters/water/time_series/test/__init__.py
kisters/water/time_series/test/old_time_series_client_async_test.py
kisters/water/time_series/test/old_time_series_client_comments_test.py
kisters/water/time_series/test/py.typed
kisters/water/time_series/test/time_series_client_async_test.py
kisters/water/time_series/test/time_series_client_comments_test.py
kisters/water/time_series/test/time_series_client_sync_test.py
kisters/water/time_series/test/time_series_store_basic_test.py
kisters_water_time_series-2.5.1.dist-info/licenses/LICENSE.txt
kisters_water_time_series-2.5.1.dist-info/METADATA
kisters_water_time_series-2.5.1.dist-info/WHEEL
kisters_water_time_series-2.5.1.dist-info/top_level.txt
kisters_water_time_series-2.5.1.dist-info/RECORD
